{
    "items": [
        {
            "id": 859,
            "type": "Sanke",
            "status": "Ended",
            "price": 225,
            "currency": "USD",
            "breeder": "Izumiya",
            "length": "44cm",
            "sex": "Female",
            "age": {
                "type": "Nisai",
                "years": 2
            },
            "image": {
                "url": "https://images.unsplash.com/photo-1515986821211-0443679c2c9e?crop=entropy&cs=srgb&fm=jpg&ixid=M3w1ODc4NDB8MHwxfHNlYXJjaHwzfHxrb2l8ZW58MHx8fHwxNzI2MDE3MDY0fDA&ixlib=rb-4.0.3&q=85"
            }
        },
        {
            "id": 860,
            "type": "Kohaku",
            "status": "Available",
            "price": 350,
            "currency": "USD",
            "breeder": "Dainichi",
            "length": "50cm",
            "sex": "Male",
            "age": {
                "type": "Sansai",
                "years": 3
            },
            "image": {
                "url": "https://th.bing.com/th/id/OIP.oRHO_MakA4wTzRnDbHQQHAHaLG?pid=ImgDetMain"
            }
        },
        {
            "id": 861,
            "type": "Showa",
            "status": "Available",
            "price": 500,
            "currency": "USD",
            "breeder": "Omosako",
            "length": "60cm",
            "sex": "Female",
            "age": {
                "type": "Yonsai",
                "years": 4
            },
            "image": {
                "url": "https://images.unsplash.com/photo-1515986821211-0443679c2c9e?crop=entropy&cs=srgb&fm=jpg&ixid=M3w1ODc4NDB8MHwxfHNlYXJjaHwzfHxrb2l8ZW58MHx8fHwxNzI2MDE3MDY0fDA&ixlib=rb-4.0.3&q=85"
            }
        },
        {
            "id": 862,
            "type": "Shusui",
            "status": "Ended",
            "price": 150,
            "currency": "USD",
            "breeder": "Maruyama",
            "length": "38cm",
            "sex": "Male",
            "age": {
                "type": "Nisai",
                "years": 2
            },
            "image": {
                "url": "https://images.unsplash.com/photo-1515986821211-0443679c2c9e?crop=entropy&cs=srgb&fm=jpg&ixid=M3w1ODc4NDB8MHwxfHNlYXJjaHwzfHxrb2l8ZW58MHx8fHwxNzI2MDE3MDY0fDA&ixlib=rb-4.0.3&q=85"
            }
        },
        {
            "id": 863,
            "type": "Tancho",
            "status": "Available",
            "price": 400,
            "currency": "USD",
            "breeder": "Sakai",
            "length": "45cm",
            "sex": "Female",
            "age": {
                "type": "Sansai",
                "years": 3
            },
            "image": {
                "url": "https://images.unsplash.com/photo-1515986821211-0443679c2c9e?crop=entropy&cs=srgb&fm=jpg&ixid=M3w1ODc4NDB8MHwxfHNlYXJjaHwzfHxrb2l8ZW58MHx8fHwxNzI2MDE3MDY0fDA&ixlib=rb-4.0.3&q=85"
            }
        },
        {
            "id": 863,
            "type": "Tancho",
            "status": "Available",
            "price": 400,
            "currency": "USD",
            "breeder": "Sakai",
            "length": "45cm",
            "sex": "Female",
            "age": {
                "type": "Sansai",
                "years": 3
            },
            "image": {
                "url": "https://images.unsplash.com/photo-1515986821211-0443679c2c9e?crop=entropy&cs=srgb&fm=jpg&ixid=M3w1ODc4NDB8MHwxfHNlYXJjaHwzfHxrb2l8ZW58MHx8fHwxNzI2MDE3MDY0fDA&ixlib=rb-4.0.3&q=85"
            }
        },
        {
            "id": 863,
            "type": "Tancho",
            "status": "Available",
            "price": 400,
            "currency": "USD",
            "breeder": "Sakai",
            "length": "45cm",
            "sex": "Female",
            "age": {
                "type": "Sansai",
                "years": 3
            },
            "image": {
                "url": "https://images.unsplash.com/photo-1515986821211-0443679c2c9e?crop=entropy&cs=srgb&fm=jpg&ixid=M3w1ODc4NDB8MHwxfHNlYXJjaHwzfHxrb2l8ZW58MHx8fHwxNzI2MDE3MDY0fDA&ixlib=rb-4.0.3&q=85"
            }
        },
        {
            "id": 863,
            "type": "Tancho",
            "status": "Available",
            "price": 400,
            "currency": "USD",
            "breeder": "Sakai",
            "length": "45cm",
            "sex": "Female",
            "age": {
                "type": "Sansai",
                "years": 3
            },
            "image": {
                "url": "https://images.unsplash.com/photo-1515986821211-0443679c2c9e?crop=entropy&cs=srgb&fm=jpg&ixid=M3w1ODc4NDB8MHwxfHNlYXJjaHwzfHxrb2l8ZW58MHx8fHwxNzI2MDE3MDY0fDA&ixlib=rb-4.0.3&q=85"
            }
        },
        {
            "id": 863,
            "type": "Tancho",
            "status": "Available",
            "price": 400,
            "currency": "USD",
            "breeder": "Sakai",
            "length": "45cm",
            "sex": "Female",
            "age": {
                "type": "Sansai",
                "years": 3
            },
            "image": {
                "url": "https://images.unsplash.com/photo-1515986821211-0443679c2c9e?crop=entropy&cs=srgb&fm=jpg&ixid=M3w1ODc4NDB8MHwxfHNlYXJjaHwzfHxrb2l8ZW58MHx8fHwxNzI2MDE3MDY0fDA&ixlib=rb-4.0.3&q=85"
            }
        },
        {
            "id": 863,
            "type": "Tancho",
            "status": "Available",
            "price": 400,
            "currency": "USD",
            "breeder": "Sakai",
            "length": "45cm",
            "sex": "Female",
            "age": {
                "type": "Sansai",
                "years": 3
            },
            "image": {
                "url": "https://images.unsplash.com/photo-1515986821211-0443679c2c9e?crop=entropy&cs=srgb&fm=jpg&ixid=M3w1ODc4NDB8MHwxfHNlYXJjaHwzfHxrb2l8ZW58MHx8fHwxNzI2MDE3MDY0fDA&ixlib=rb-4.0.3&q=85"
            }
        },
        {
            "id": 863,
            "type": "Tancho",
            "status": "Available",
            "price": 400,
            "currency": "USD",
            "breeder": "Sakai",
            "length": "45cm",
            "sex": "Female",
            "age": {
                "type": "Sansai",
                "years": 3
            },
            "image": {
                "url": "https://images.unsplash.com/photo-1515986821211-0443679c2c9e?crop=entropy&cs=srgb&fm=jpg&ixid=M3w1ODc4NDB8MHwxfHNlYXJjaHwzfHxrb2l8ZW58MHx8fHwxNzI2MDE3MDY0fDA&ixlib=rb-4.0.3&q=85"
            }
        },
        {
            "id": 863,
            "type": "Tancho",
            "status": "Available",
            "price": 400,
            "currency": "USD",
            "breeder": "Sakai",
            "length": "45cm",
            "sex": "Female",
            "age": {
                "type": "Sansai",
                "years": 3
            },
            "image": {
                "url": "https://images.unsplash.com/photo-1515986821211-0443679c2c9e?crop=entropy&cs=srgb&fm=jpg&ixid=M3w1ODc4NDB8MHwxfHNlYXJjaHwzfHxrb2l8ZW58MHx8fHwxNzI2MDE3MDY0fDA&ixlib=rb-4.0.3&q=85"
            }
        }
    ]
}